setup.py
unrealistic/__init__.py
unrealistic/drive.py
unrealistic.egg-info/PKG-INFO
unrealistic.egg-info/SOURCES.txt
unrealistic.egg-info/dependency_links.txt
unrealistic.egg-info/top_level.txt
unrealistic/environment/__init__.py
unrealistic/environment/env.py
unrealistic/environment/animals/Dog.py
unrealistic/environment/animals/__init__.py
unrealistic/environment/animals/animalia.py