Metadata-Version: 2.1
Name: unrealistic
Version: 0.0.11
Summary: Nothing.
Home-page: UNKNOWN
Author: Wit
Author-email: airesntt@arisetn.seu
License: UNKNOWN
Platform: UNKNOWN
Classifier: Programming Language :: Python :: 3
Classifier: License :: OSI Approved :: MIT License
